odoo8_addon_sale_quotation_number-8.0.1.1.0.99.dev13-py3.8-nspkg.pth
odoo_addons/sale_quotation_number/AUTHORS.txt
odoo_addons/sale_quotation_number/__init__.py
odoo_addons/sale_quotation_number/__openerp__.py
odoo_addons/sale_quotation_number/data/data.xml
odoo_addons/sale_quotation_number/i18n/ca.po
odoo_addons/sale_quotation_number/i18n/de.po
odoo_addons/sale_quotation_number/i18n/es.po
odoo_addons/sale_quotation_number/i18n/es_ES.po
odoo_addons/sale_quotation_number/i18n/fi.po
odoo_addons/sale_quotation_number/i18n/fr.po
odoo_addons/sale_quotation_number/i18n/hr.po
odoo_addons/sale_quotation_number/i18n/hu.po
odoo_addons/sale_quotation_number/i18n/it.po
odoo_addons/sale_quotation_number/i18n/nl.po
odoo_addons/sale_quotation_number/i18n/nl_NL.po
odoo_addons/sale_quotation_number/i18n/pt_BR.po
odoo_addons/sale_quotation_number/i18n/ro.po
odoo_addons/sale_quotation_number/i18n/sale_quotation_number.pot
odoo_addons/sale_quotation_number/i18n/sk.po
odoo_addons/sale_quotation_number/i18n/sl.po
odoo_addons/sale_quotation_number/i18n/tr.po
odoo_addons/sale_quotation_number/i18n/tr_TR.po
odoo_addons/sale_quotation_number/i18n/zh_CN.po
odoo_addons/sale_quotation_number/model/__init__.py
odoo_addons/sale_quotation_number/model/sale_order.py
odoo_addons/sale_quotation_number/static/description/icon.png
odoo8_addon_sale_quotation_number-8.0.1.1.0.99.dev13.dist-info/METADATA
odoo8_addon_sale_quotation_number-8.0.1.1.0.99.dev13.dist-info/WHEEL
odoo8_addon_sale_quotation_number-8.0.1.1.0.99.dev13.dist-info/namespace_packages.txt
odoo8_addon_sale_quotation_number-8.0.1.1.0.99.dev13.dist-info/top_level.txt
odoo8_addon_sale_quotation_number-8.0.1.1.0.99.dev13.dist-info/RECORD
