Metadata-Version: 2.1
Name: odoo8-addon-sale-quotation-number
Version: 8.0.1.1.0.99.dev13
Summary: Different sequence for sale quotations
Home-page: http://www.openerp.net.cn
Author: Elico Corp,Agile Business Group,Odoo Community Association (OCA)
Author-email: support@odoo-community.org
License: UNKNOWN
Platform: UNKNOWN
Classifier: Programming Language :: Python
Classifier: Framework :: Odoo
Classifier: Framework :: Odoo :: 8.0
Requires-Python: ~=2.7
Requires-Dist: odoo (<9.0a,>=8.0a)
